qri/__init__.py
qri/__version__.py
qri/client.py
qri/cmd_util.py
qri/dataset.py
qri/dsref.py
qri/error.py
qri/loader.py
qri/util.py
qri/version_info.py
qri-0.1.5.dist-info/LICENSE
qri-0.1.5.dist-info/METADATA
qri-0.1.5.dist-info/WHEEL
qri-0.1.5.dist-info/top_level.txt
qri-0.1.5.dist-info/RECORD
