Metadata-Version: 2.1
Name: qri
Version: 0.1.5
Summary: qri python client
Home-page: https://github.com/qri-io/qri-python
Author: Dustin Long
Author-email: dustmop@qri.io
License: UNKNOWN
Platform: UNKNOWN
Classifier: Programming Language :: Python
Classifier: License :: OSI Approved :: MIT License
Requires-Python: >=3.6
Requires-Dist: pandas (==1.0.0)
Requires-Dist: Markdown (==3.2.2)
Requires-Dist: requests (==2.24.0)
